mf/__init__.py
mf/cli_cache.py
mf/cli_config.py
mf/cli_last.py
mf/cli_main.py
mf/constants.py
mf/version.py
mf/utils/cache.py
mf/utils/config.py
mf/utils/console.py
mf/utils/file.py
mf/utils/generate_dummy_media.py
mf/utils/library.py
mf/utils/misc.py
mf/utils/normalizers.py
mf/utils/parsers.py
mf/utils/play.py
mf/utils/playlist.py
mf/utils/scan.py
mf/utils/search.py
mf/utils/settings.py
mf/utils/stats.py
mf/utils/validation.py
mf/bin/LICENSE-fd-APACHE
mf/bin/LICENSE-fd-MIT
mf/bin/fd-v10_3_0-aarch64-apple-darwin
mf/bin/fd-v10_3_0-x86_64-apple-darwin
mf/bin/fd-v10_3_0-x86_64-pc-windows-msvc.exe
mf/bin/fd-v10_3_0-x86_64-unknown-linux-gnu
mediafinder-0.11.0.dist-info/METADATA
mediafinder-0.11.0.dist-info/WHEEL
mediafinder-0.11.0.dist-info/entry_points.txt
mediafinder-0.11.0.dist-info/licenses/LICENSE-MIT
mediafinder-0.11.0.dist-info/RECORD
