Metadata-Version: 2.4
Name: mediafinder
Version: 0.11.0
Summary: Media file finder and player
Project-URL: Homepage, https://github.com/aplzr/mf
Project-URL: Issues, https://github.com/aplzr/mf/issues
Author-email: ap <arnepelzerprivat@gmail.com>
License: MIT License
License-File: LICENSE-MIT
Keywords: cli,filesystem,finder,media,player,video
Classifier: Development Status :: 4 - Beta
Classifier: Environment :: Console
Classifier: Intended Audience :: End Users/Desktop
Classifier: License :: OSI Approved :: MIT License
Classifier: Natural Language :: English
Classifier: Operating System :: OS Independent
Classifier: Programming Language :: Python :: 3
Classifier: Programming Language :: Python :: 3 :: Only
Classifier: Programming Language :: Python :: 3.10
Classifier: Programming Language :: Python :: 3.11
Classifier: Programming Language :: Python :: 3.12
Classifier: Programming Language :: Python :: 3.13
Classifier: Programming Language :: Python :: 3.14
Classifier: Topic :: Multimedia :: Video
Classifier: Topic :: System :: Filesystems
Classifier: Topic :: Utilities
Requires-Python: >=3.10
Requires-Dist: guessit>=3.8.0
Requires-Dist: imdbinfo>=0.6.3
Requires-Dist: packaging>=25.0
Requires-Dist: patool>=4.0.1
Requires-Dist: rich>=14.2.0
Requires-Dist: tomlkit>=0.13.3
Requires-Dist: typer>=0.19.2
Provides-Extra: dev
Requires-Dist: anybadge>=1.10.0; extra == 'dev'
Requires-Dist: mypy>=1.19.1; extra == 'dev'
Requires-Dist: prek>=0.2.23; extra == 'dev'
Requires-Dist: pytest-cov>=5.0.0; extra == 'dev'
Requires-Dist: pytest>=8.3.0; extra == 'dev'
Requires-Dist: ruff>=0.14.3; extra == 'dev'
Requires-Dist: rust-just>=1.45.0; extra == 'dev'
